picross/__init__.py
picross/__main__.py
picross/about_pages.py
picross/conf.py
picross/document.py
picross/download.py
picross/gemini_url.py
picross/tofu.py
picross/transport.py
picross/gui/__init__.py
picross/gui/controller.py
picross/gui/dialog.py
picross/gui/model.py
picross/gui/view.py
picross/gui/widgets.py
picross-0.6.2.dist-info/LICENSE
picross-0.6.2.dist-info/METADATA
picross-0.6.2.dist-info/WHEEL
picross-0.6.2.dist-info/entry_points.txt
picross-0.6.2.dist-info/top_level.txt
picross-0.6.2.dist-info/RECORD
