Metadata-Version: 2.1
Name: picross
Version: 0.6.2
Summary: Python/Tk GUI browser for Gemini
Home-page: https://git.sr.ht/~fkfd/picross
Author: Frederick Yin
Author-email: fkfd@macaw.me
License: UNKNOWN
Platform: UNKNOWN
Requires-Python: >=3.7,<4.0
Requires-Dist: appdirs (<2.0.0,>=1.4.4)
Requires-Dist: curio (<2.0,>=1.2)
Requires-Dist: toml (<0.11.0,>=0.10.1)
Requires-Dist: cryptography (<4.0.0,>=3.0.0)
Requires-Dist: python-dateutil (<3.0.0,>=2.7.0)
